README.md
setup.py
teahaz/__init__.py
teahaz/client.py
teahaz/dataclasses.py
teahaz/types.py
teahaz.py.egg-info/PKG-INFO
teahaz.py.egg-info/SOURCES.txt
teahaz.py.egg-info/dependency_links.txt
teahaz.py.egg-info/requires.txt
teahaz.py.egg-info/top_level.txt