Metadata-Version: 2.1
Name: teahaz.py
Version: 0.1.0
Summary: The official Python API wrapper for the Teaház protocol.
Home-page: https://github.com/bczsalba/teahaz.py
Author: BcZsalba
Author-email: bczsalba@gmail.com
License: MIT
Platform: UNKNOWN
